{
  "fileName": "DragHandle.tsx",
  "filePath": "weave-js/src/common/containers/DragDropContainer/DragHandle.tsx",
  "url": "https://github.com/wandb/weave/weave-js/src/common/containers/DragDropContainer/DragHandle.tsx",
  "summary": "The code above is a React component that provides a drag handle for a draggable element. It is part of the larger project called Weave. The component is imported from two other files, `DragDropContextProvider` and `types`. \n\nThe `DragHandle` component takes in four props: `partRef`, `children`, `className`, and `style`. `partRef` is a reference to the draggable element that the handle is associated with. `children` is the content that will be displayed inside the handle. `className` and `style` are optional props that allow for custom styling of the handle.\n\nThe component uses the `useContext` hook to access the `DragDropContext` object, which is provided by the `DragDropContextProvider`. The `DragDropContext` object contains two functions, `setDragRef` and `setMouseDownEvent`, which are used to set the reference to the draggable element and the mouse down event, respectively.\n\nWhen the handle is clicked (`onMouseDown`), the `setDragRef` function is called with the `partRef` prop, which sets the reference to the draggable element. The `setMouseDownEvent` function is also called with the mouse down event, which is used to calculate the drag distance when the element is dragged.\n\nThe `DragHandle` component returns a `div` element with the `drag-drop-handle` class and any additional classes passed in through the `className` prop. The `style` prop is used to apply any custom styles to the handle. The `children` prop is rendered inside the `div` element.\n\nThe `DragHandle` component is memoized using the `memo` function, which improves performance by preventing unnecessary re-renders of the component.\n\nThis component can be used in conjunction with other components in the Weave project to create draggable elements with drag handles. For example, a user could drag a chart element by clicking and dragging on the drag handle. \n\nExample usage:\n\n```\n<DragHandle partRef={chartRef} className=\"chart-drag-handle\">\n  <div className=\"drag-handle-icon\">Drag</div>\n</DragHandle>\n```",
  "questions": "1. What is the purpose of the `DragHandle` component?\n   - The `DragHandle` component is used as a handle for drag and drop functionality in the `weave` project.\n\n2. What is the `DragDropContext` and how is it used in this code?\n   - The `DragDropContext` is imported from `./DragDropContextProvider` and is used to provide context for drag and drop functionality in the `DragHandleComp` component.\n\n3. What is the purpose of the `memo` function in the export statement?\n   - The `memo` function is used to memoize the `DragHandleComp` component, which can improve performance by preventing unnecessary re-renders."
}