{
  "fileName": "string.ts",
  "filePath": "weave-js/src/common/util/string.ts",
  "url": "https://github.com/wandb/weave/weave-js/src/common/util/string.ts",
  "summary": "The `weave` project includes a file with various utility functions for string manipulation. These functions can be used throughout the project to perform common string operations.\n\nThe `splitOnce` function takes in a string and a delimiter and returns an array with two elements: the substring before the first occurrence of the delimiter and the substring after the delimiter. If the delimiter is not present in the string, the function returns an array with the original string and a null value. For example:\n\n```\nsplitOnce('hello-world', '-') // returns ['hello', 'world']\nsplitOnce('hello', '-') // returns ['hello', null]\n```\n\nThe `splitOnceLast` function is similar to `splitOnce`, but it returns the substring before the last occurrence of the delimiter and the substring after the last occurrence of the delimiter. If the delimiter is not present in the string, the function returns an array with two null values. For example:\n\n```\nsplitOnceLast('hello-world', '-') // returns ['hello', 'world']\nsplitOnceLast('hello-world-hi', '-') // returns ['hello-world', 'hi']\nsplitOnceLast('hello', '-') // returns [null, null]\n```\n\nThe `stripQuotesAndSpace` function takes in a string and removes any leading or trailing quotes or whitespace. If the input is not a string, the function returns the input unchanged.\n\nThe `sanitizeGQLAlias` function takes in a string and replaces any non-letter, non-number, or non-underscore characters with double underscores. This function is useful for ensuring that a string can be used as a valid GraphQL alias.\n\nThe `capitalizeFirst` function takes in a string and capitalizes the first letter while making the rest of the string lowercase.\n\nThe `isValidEmail` function takes in a string and returns true if the string matches the pattern of a valid email address.\n\nThe `removeNonASCII` function takes in a string and removes any non-ASCII characters.\n\nThe `indent` function takes in a string and a number representing the indentation level and returns the string with the specified number of spaces added to the beginning of each line.\n\nThe `applyPrefixIfNeeded` function takes in a prefix and a string and returns the string with the prefix added if it is not already present.\n\nThe `stripPrefixesIfNeeded` function takes in an array of prefixes and a string and returns the string with any of the specified prefixes removed from the beginning.\n\nThe `replaceDashWithSpace` function takes in a string and replaces any dashes with spaces.\n\nOverall, these utility functions provide a convenient way to perform common string operations throughout the `weave` project.",
  "questions": "1. What is the purpose of the `StringUtil` import from `lodash`?\n- A smart developer might ask what specific utility functions from `StringUtil` are being used in this file.\n\n2. What is the expected input and output of the `splitOnce` and `splitOnceLast` functions?\n- A smart developer might ask for more information on the expected input and output types of the `splitOnce` and `splitOnceLast` functions, as well as how they differ from each other.\n\n3. What is the purpose of the `sanitizeGQLAlias` function?\n- A smart developer might ask why the `sanitizeGQLAlias` function is needed and how it is used in the larger project."
}